.gitignore
LICENSE
MANIFEST.in
README.md
setup.py
doc/Doxyfile
locale/es.po
locale/fr.po
locale/swapping_ebuilds.pot
swapping_ebuilds/__init__.py
swapping_ebuilds/main.py
swapping_ebuilds.egg-info/PKG-INFO
swapping_ebuilds.egg-info/SOURCES.txt
swapping_ebuilds.egg-info/dependency_links.txt
swapping_ebuilds.egg-info/entry_points.txt
swapping_ebuilds.egg-info/not-zip-safe
swapping_ebuilds.egg-info/requires.txt
swapping_ebuilds.egg-info/top_level.txt
swapping_ebuilds/images/swapping_ebuilds_doxygen.png
swapping_ebuilds/locale/es/LC_MESSAGES/swapping_ebuilds.mo
swapping_ebuilds/locale/fr/LC_MESSAGES/swapping_ebuilds.mo