Metadata-Version: 2.1
Name: swapping-ebuilds
Version: 0.2.0
Summary: Script to detect swapping compiling ebuilds in Gentoo
Home-page: https://github.com/turulomio/swapping_ebuilds
Author: turulomio
Author-email: turulomio@yahoo.es
License: GPL-3
Keywords: swap ebuild gentoo portage
Platform: UNKNOWN
Classifier: Development Status :: 4 - Beta
Classifier: Intended Audience :: System Administrators
Classifier: Topic :: System :: Systems Administration
Classifier: License :: OSI Approved :: GNU General Public License v3 (GPLv3)
Classifier: Programming Language :: Python :: 3
